{
  "updatedAt": "2026-07-15 13:52:46",
  "stocks": [
    {
      "id": 10001,
      "name": "台G電",
      "description": "晶片科技股",
      "base_price": 7230,
      "current_price": 5254,
      "today_open": 6188,
      "today_high": 7528,
      "today_low": 5201,
      "volume_24h": 43112,
      "change_amount": -934,
      "change_percent": -15.0937,
      "last_update": "2026-07-15 13:44:00"
    },
    {
      "id": 10002,
      "name": "落葉AI工作室",
      "description": "AI與科技概念股",
      "base_price": 3750,
      "current_price": 3246,
      "today_open": 3033,
      "today_high": 3648,
      "today_low": 2938,
      "volume_24h": 2663,
      "change_amount": 213,
      "change_percent": 7.0227,
      "last_update": "2026-07-15 13:44:00"
    },
    {
      "id": 10003,
      "name": "陳弱莊斗雞學院",
      "description": "娛樂教育概念股",
      "base_price": 4107,
      "current_price": 3171,
      "today_open": 3152,
      "today_high": 3549,
      "today_low": 3026,
      "volume_24h": 100,
      "change_amount": 19,
      "change_percent": 0.6028,
      "last_update": "2026-07-15 13:44:00"
    },
    {
      "id": 10004,
      "name": "19茶屋",
      "description": "手搖飲品牌股",
      "base_price": 9203,
      "current_price": 4657,
      "today_open": 4927,
      "today_high": 5430,
      "today_low": 4355,
      "volume_24h": 4455,
      "change_amount": -270,
      "change_percent": -5.48,
      "last_update": "2026-07-15 13:44:00"
    },
    {
      "id": 10005,
      "name": "廖老二手搖飲",
      "description": "飲料連鎖概念股",
      "base_price": 3000,
      "current_price": 2440,
      "today_open": 2492,
      "today_high": 2502,
      "today_low": 2146,
      "volume_24h": 427113,
      "change_amount": -52,
      "change_percent": -2.0867,
      "last_update": "2026-07-15 13:44:00"
    },
    {
      "id": 10006,
      "name": "豬皮購物",
      "description": "電商購物股",
      "base_price": 4344,
      "current_price": 2558,
      "today_open": 2943,
      "today_high": 3009,
      "today_low": 2522,
      "volume_24h": 100,
      "change_amount": -385,
      "change_percent": -13.0819,
      "last_update": "2026-07-15 13:44:00"
    },
    {
      "id": 10007,
      "name": "特會拉電動車",
      "description": "電動車能源股",
      "base_price": 8431,
      "current_price": 3860,
      "today_open": 4658,
      "today_high": 5721,
      "today_low": 3771,
      "volume_24h": 15622,
      "change_amount": -798,
      "change_percent": -17.1318,
      "last_update": "2026-07-15 13:44:00"
    },
    {
      "id": 10008,
      "name": "Eagle航空",
      "description": "航空運輸股",
      "base_price": 3984,
      "current_price": 2760,
      "today_open": 2883,
      "today_high": 3128,
      "today_low": 2733,
      "volume_24h": 3714,
      "change_amount": -123,
      "change_percent": -4.2664,
      "last_update": "2026-07-15 13:44:00"
    },
    {
      "id": 10009,
      "name": "H逼D微商",
      "description": "",
      "base_price": 5200,
      "current_price": 3611,
      "today_open": 3799,
      "today_high": 3879,
      "today_low": 3486,
      "volume_24h": 17429,
      "change_amount": -188,
      "change_percent": -4.9487,
      "last_update": "2026-07-15 13:44:00"
    },
    {
      "id": 10010,
      "name": "泉願格鬥",
      "description": "",
      "base_price": 6100,
      "current_price": 4573,
      "today_open": 4923,
      "today_high": 5362,
      "today_low": 4567,
      "volume_24h": 100,
      "change_amount": -350,
      "change_percent": -7.1095,
      "last_update": "2026-07-15 13:44:00"
    },
    {
      "id": 10011,
      "name": "ETF穩健指數",
      "description": "長期投資型 ETF，低波動、低回報但相對穩定",
      "base_price": 6500,
      "current_price": 6451,
      "today_open": 5878,
      "today_high": 7028,
      "today_low": 5693,
      "volume_24h": 100,
      "change_amount": 573,
      "change_percent": 9.7482,
      "last_update": "2026-07-15 13:44:00"
    },
    {
      "id": 10012,
      "name": "人工智障GPT",
      "description": "號稱最強AI，回答起來一本正經卻常常胡說八道，投資人心臟要夠大顆。",
      "base_price": 8888,
      "current_price": 4748,
      "today_open": 5099,
      "today_high": 5171,
      "today_low": 4645,
      "volume_24h": 22980,
      "change_amount": -351,
      "change_percent": -6.8837,
      "last_update": "2026-07-15 13:44:00"
    }
  ]
}