{
  "updatedAt": "2026-07-01 21:18:01",
  "stocks": [
    {
      "id": 10001,
      "name": "台G電",
      "description": "晶圓代工龍頭，科技股指標",
      "base_price": 7230,
      "current_price": 6182,
      "today_open": 6203,
      "today_high": 6203,
      "today_low": 6151,
      "volume_24h": 334,
      "change_amount": -21,
      "change_percent": -0.3385,
      "last_update": "2026-07-01 21:10:00"
    },
    {
      "id": 10002,
      "name": "落葉谷工作室",
      "description": "獨立遊戲開發商，創意爆發",
      "base_price": 3750,
      "current_price": 3222,
      "today_open": 3231,
      "today_high": 3249,
      "today_low": 3211,
      "volume_24h": 256,
      "change_amount": -9,
      "change_percent": -0.2786,
      "last_update": "2026-07-01 21:10:00"
    },
    {
      "id": 10003,
      "name": "陳菊溼汗健身房",
      "description": "健康風潮引爆，全楓之谷展店最快品牌",
      "base_price": 4107,
      "current_price": 3677,
      "today_open": 3648,
      "today_high": 3678,
      "today_low": 3648,
      "volume_24h": 304,
      "change_amount": 29,
      "change_percent": 0.795,
      "last_update": "2026-07-01 21:10:00"
    },
    {
      "id": 10004,
      "name": "19茶屋",
      "description": "精品手搖飲品牌，主打高端市場",
      "base_price": 9203,
      "current_price": 8385,
      "today_open": 8431,
      "today_high": 8460,
      "today_low": 8385,
      "volume_24h": 228,
      "change_amount": -46,
      "change_percent": -0.5456,
      "last_update": "2026-07-01 21:10:00"
    },
    {
      "id": 10005,
      "name": "廖老二手搖飲",
      "description": "連鎖茶飲集團，年輕族群最愛",
      "base_price": 3000,
      "current_price": 2831,
      "today_open": 2797,
      "today_high": 2831,
      "today_low": 2797,
      "volume_24h": 273,
      "change_amount": 34,
      "change_percent": 1.2156,
      "last_update": "2026-07-01 21:10:00"
    },
    {
      "id": 10006,
      "name": "豬皮購物",
      "description": "電商平台新秀，物流速度傲視同業",
      "base_price": 4344,
      "current_price": 3820,
      "today_open": 3825,
      "today_high": 3825,
      "today_low": 3802,
      "volume_24h": 242,
      "change_amount": -5,
      "change_percent": -0.1307,
      "last_update": "2026-07-01 21:10:00"
    },
    {
      "id": 10007,
      "name": "特會拉電動車",
      "description": "綠能運輸革命，訂單爆滿",
      "base_price": 8431,
      "current_price": 8178,
      "today_open": 8141,
      "today_high": 8178,
      "today_low": 8043,
      "volume_24h": 331,
      "change_amount": 37,
      "change_percent": 0.4545,
      "last_update": "2026-07-01 21:10:00"
    },
    {
      "id": 10008,
      "name": "Eagle精品",
      "description": "奢侈品龍頭，限量聯名",
      "base_price": 3984,
      "current_price": 3613,
      "today_open": 3657,
      "today_high": 3677,
      "today_low": 3613,
      "volume_24h": 301,
      "change_amount": -44,
      "change_percent": -1.2032,
      "last_update": "2026-07-01 21:10:00"
    },
    {
      "id": 10009,
      "name": "H逼D微商",
      "description": "高風險高波動微商概念股",
      "base_price": 5200,
      "current_price": 4813,
      "today_open": 4829,
      "today_high": 4829,
      "today_low": 4810,
      "volume_24h": 210,
      "change_amount": -16,
      "change_percent": -0.3313,
      "last_update": "2026-07-01 21:10:00"
    },
    {
      "id": 10010,
      "name": "泉願格鬥",
      "description": "格鬥娛樂與競技活動品牌",
      "base_price": 6100,
      "current_price": 5601,
      "today_open": 5603,
      "today_high": 5626,
      "today_low": 5560,
      "volume_24h": 290,
      "change_amount": -2,
      "change_percent": -0.0357,
      "last_update": "2026-07-01 21:10:00"
    },
    {
      "id": 10011,
      "name": "ETF穩健指數",
      "description": "長期投資型 ETF，低波動、低回報但相對穩定",
      "base_price": 6500,
      "current_price": 6004,
      "today_open": 5999,
      "today_high": 6004,
      "today_low": 5995,
      "volume_24h": 246,
      "change_amount": 5,
      "change_percent": 0.0833,
      "last_update": "2026-07-01 21:10:00"
    }
  ]
}